i3bindings/__init__.py
i3bindings/__main__.py
i3bindings/cli.py
i3bindings/constants.py
i3bindings/io.py
i3bindings/node.py
i3bindings/random_input_generator.py
i3bindings/tree_algorithms.py
i3bindings/tree_parser.py
i3bindings-1.0.0a1.dist-info/entry_points.txt
i3bindings-1.0.0a1.dist-info/LICENSE
i3bindings-1.0.0a1.dist-info/WHEEL
i3bindings-1.0.0a1.dist-info/METADATA
i3bindings-1.0.0a1.dist-info/RECORD
