Metadata-Version: 2.1
Name: i3bindings
Version: 1.0.0a1
Summary: 
Home-page: https://github.com/ViliamV/i3bindings
License: MIT
Keywords: i3,bspwm
Author: Viliam Valent
Author-email: i3bindings@viliamvalent.com
Requires-Python: >=3.7,<4.0
Classifier: License :: OSI Approved :: MIT License
Classifier: Programming Language :: Python :: 3
Classifier: Programming Language :: Python :: 3.7
Classifier: Programming Language :: Python :: 3.8
Project-URL: Repository, https://github.com/ViliamV/i3bindings
